{
  "notifications": [
    {
      "id": 0,
      "userId": 1,
      "text": "О нет это же еще обычный текст"
    }
  ],
  "tags": [
    {
      "type": "ANIMALS",
      "amount": 62
    },
    {
      "type": "TECHNOLOGIES",
      "amount": 22
    },
    {
      "type": "HUMOR",
      "amount": 101
    }
  ],
  "users": [
    {
      "id": 1,
      "login": "Sergey",
      "password": "1234",
      "status": "Хаха",
      "headerTheme": "Default",
      "ignoreList": {
        "tags": [
          "TECHNOLOGIES",
          "ANIMALS"
        ]
      },
      "systemRole": "ADMIN",
      "newNotifications": true,
      "avatar": {
        "src": "https://www.clubvillamar.com/blog/wp-content/uploads/2018/01/mountain-hiking-1.jpg",
        "alt": ""
      }
    },
    {
      "id": 99,
      "login": "Volibear",
      "password": "hello",
      "status": "Хаха",
      "headerTheme": "Orange",
      "ignoreList": {
        "tags": []
      },
      "systemRole": "USER",
      "newNotifications": true,
      "avatar": {
        "src": "https://ih1.redbubble.net/image.1276588976.2208/flat,750x1000,075,t.jpg",
        "alt": ""
      }
    },
    {
      "id": 123,
      "login": "Kiselev_Sergey",
      "status": "Опаньки",
      "password": "qwerty12312",
      "headerTheme": "Gold",
      "ignoreList": {
        "tags": [
          "HUMOR"
        ]
      },
      "systemRole": "USER",
      "newNotifications": true,
      "avatar": {
        "src": "https://www.clubvillamar.com/blog/wp-content/uploads/2018/01/mountain-hiking-1.jpg",
        "alt": ""
      }
    },
    {
      "id": 23,
      "login": "Vera_xxx",
      "status": "Новый статус",
      "password": "qwerty12312",
      "headerTheme": "Aqua",
      "ignoreList": {
        "tags": []
      },
      "systemRole": "USER",
      "newNotifications": true,
      "avatar": {
        "src": "https://i.pinimg.com/originals/85/70/2b/85702b6d8d71518b6feb0c636081f26d.jpg",
        "alt": ""
      }
    }
  ],
  "posts": [
    {
      "id": 12,
      "title": "Тестовый пост сложный",
      "timestamp": 1686062966913,
      "author_id": 123,
      "views": 465,
      "content": [
        {
          "type": "TEXT",
          "text": "Разнообразный и богатый опыт говорит нам, что граница обучения кадров однозначно определяет каждого участника как способного принимать собственные решения касаемо дальнейших направлений развития. В частности, существующая теория позволяет выполнить важные задания по разработке как самодостаточных, так и внешне зависимых концептуальных решений."
        },
        {
          "type": "TEXT",
          "text": "Принимая во внимание показатели успешности, высококачественный прототип будущего проекта позволяет оценить значение кластеризации усилий."
        },
        {
          "type": "QUOTE",
          "text": "Как говорил мне мой дед - я твой дед"
        },
        {
          "type": "IMAGE",
          "image": {
            "src": "https://www.clubvillamar.com/blog/wp-content/uploads/2018/01/mountain-hiking-1.jpg",
            "alt": ""
          }
        }
      ],
      "tags": [
        "HUMOR",
        "ANIMALS"
      ]
    },
    {
      "id": 14,
      "title": "Еще блин один пост",
      "timestamp": 1686062666913,
      "author_id": 23,
      "views": 94,
      "content": [
        {
          "type": "TEXT",
          "text": "Обычный текст"
        },
        {
          "type": "IMAGE",
          "image": {
            "src": "https://i.internetdaybook.com/images/027/image-78612-2.jpg",
            "alt": ""
          }
        },
        {
          "type": "TEXT",
          "text": "О нет это же еще обычный текст"
        }
      ],
      "tags": [
        "TECHNOLOGIES",
        "ANIMALS"
      ]
    },
    {
      "id": 16,
      "title": "Смешной пост про айти",
      "timestamp": 1689062966913,
      "author_id": 23,
      "views": 700,
      "content": [
        {
          "type": "IMAGE",
          "image": {
            "src": "https://fikiwiki.com/uploads/posts/2022-02/1644925850_42-fikiwiki-com-p-prikolnie-kartinki-pro-programmistov-45.jpg",
            "alt": ""
          }
        }
      ],
      "tags": [
        "TECHNOLOGIES",
        "HUMOR"
      ]
    },
    {
      "id": 1562,
      "title": "«Какие дети?! Новый фреймворк вышел!»⁠⁠",
      "timestamp": 1686862365913,
      "author_id": 123,
      "views": 2234,
      "content": [
        {
          "type": "IMAGE",
          "image": {
            "src": "https://cs13.pikabu.ru/post_img/2023/05/26/4/168507954111362216.webp",
            "alt": ""
          }
        }
      ],
      "tags": [
        "TECHNOLOGIES"
      ]
    },
    {
      "id": 1672,
      "title": "При помощи нейросети от Photoshop, дорисовал популярные картины⁠",
      "timestamp": 1646868365913,
      "author_id": 123,
      "views": 28939,
      "content": [
        {
          "type": "IMAGE",
          "image": {
            "src": "https://cs13.pikabu.ru/post_img/2023/06/07/9/1686150777122714744.webp",
            "alt": ""
          }
        },
        {
          "type": "IMAGE",
          "image": {
            "src": "https://cs13.pikabu.ru/post_img/2023/06/07/9/168615076718829477.webp",
            "alt": ""
          }
        },
        {
          "type": "IMAGE",
          "image": {
            "src": "https://cs13.pikabu.ru/post_img/2023/06/07/9/1686150787152517275.webp",
            "alt": ""
          }
        },
        {
          "type": "QUOTE",
          "text": "Любая достаточно развитая технология неотличима от магии."
        }
      ],
      "tags": [
        "TECHNOLOGIES"
      ]
    },
    {
      "id": 1590,
      "title": "Заголовок поста #2⁠⁠⁠⁠",
      "timestamp": 1686862365913,
      "author_id": 123,
      "views": 9230,
      "content": [
        {
          "type": "TEXT",
          "text": "Kočka žere žradlo"
        },
        {
          "type": "IMAGE",
          "image": {
            "src": "https://cs14.pikabu.ru/post_img/2023/06/14/11/1686770544173839263.webp",
            "alt": ""
          }
        }
      ],
      "tags": [
        "ANIMALS"
      ]
    },
    {
      "id": 180,
      "title": "Правила делового общения⁠⁠⁠⁠",
      "timestamp": 1686862365913,
      "author_id": 123,
      "views": 26735,
      "content": [
        {
          "type": "IMAGE",
          "image": {
            "src": "https://cs13.pikabu.ru/post_img/2023/06/15/7/168682720619336508.webp",
            "alt": ""
          }
        }
      ],
      "tags": [
        "ANIMALS"
      ]
    },
    {
      "title": "Жесть как она есть",
      "content": [
        {
          "type": "TEXT",
          "text": "hehehehhehe"
        }
      ],
      "tags": [],
      "timestamp": 1691183042535,
      "author_id": 99,
      "views": 37,
      "id": 1679
    },
    {
      "title": "ujhknn,",
      "content": [
        {
          "type": "TEXT",
          "text": "hehehehhehe"
        }
      ],
      "tags": [],
      "author_id": 23,
      "timestamp": 1691410046804,
      "views": 0,
      "id": 1680
    },
    {
      "title": "ggggggggg",
      "content": [
        {
          "type": "TEXT",
          "text": "hehehehhehe"
        }
      ],
      "tags": [],
      "author_id": 23,
      "timestamp": 1691410093952,
      "views": 0,
      "id": 1681
    },
    {
      "title": "fffffffffff",
      "content": [
        {
          "type": "TEXT",
          "text": "hehehehhehe"
        }
      ],
      "tags": [],
      "author_id": 23,
      "timestamp": 1691410149023,
      "views": 0,
      "id": 1682
    },
    {
      "title": "хкхкхккхкх",
      "content": [
        {
          "type": "TEXT",
          "text": "hehehehhehe"
        }
      ],
      "tags": [],
      "author_id": 23,
      "timestamp": 1691410209445,
      "views": 0,
      "id": 1683
    },
    {
      "title": "dada",
      "content": [
        {
          "type": "TEXT",
          "text": "hehehehhehe"
        }
      ],
      "tags": [],
      "author_id": 23,
      "timestamp": 1691410953206,
      "views": 0,
      "id": 1684
    },
    {
      "title": "POST BY ADMIN",
      "content": [
        {
          "type": "TEXT",
          "text": "hehehehhehe"
        }
      ],
      "tags": [],
      "author_id": 1,
      "timestamp": 1691424542623,
      "views": 0,
      "id": 1685
    },
    {
      "title": "HELLO WORLD!",
      "content": [
        {
          "type": "TEXT",
          "text": "hehehehhehe"
        }
      ],
      "tags": [],
      "author_id": 99,
      "timestamp": 1691501861691,
      "views": 0,
      "id": 1686
    }
  ],
  "comments": [
    {
      "id": 0,
      "post_id": 12,
      "user_id": 23,
      "text": "О нет это же еще обычный текст",
      "timestamp": 1646868365913
    }
  ],
  "likes": [
    {
      "post_id": 16,
      "user_id": 23,
      "id": 2
    },
    {
      "post_id": 12,
      "user_id": 23,
      "id": 3
    },
    {
      "post_id": 1684,
      "user_id": 99,
      "id": 5
    },
    {
      "post_id": 180,
      "user_id": 99,
      "id": 8
    },
    {
      "post_id": 1672,
      "user_id": 99,
      "id": 10
    },
    {
      "post_id": 1590,
      "user_id": 99,
      "id": 11
    }
  ],
  "usersSubscriptions": [
    {
      "id": 0,
      "subscribed_by": 99,
      "subscribed_on": 123
    },
    {
      "id": 1,
      "subscribed_by": 123,
      "subscribed_on": 99
    }
  ],
  "saves": [
    {
      "post_id": 1683,
      "user_id": 23,
      "id": 1
    },
    {
      "post_id": 1684,
      "user_id": 23,
      "id": 2
    },
    {
      "post_id": 12,
      "user_id": 23,
      "id": 3
    },
    {
      "post_id": 14,
      "user_id": 99,
      "id": 10
    },
    {
      "post_id": 12,
      "user_id": 99,
      "id": 11
    },
    {
      "post_id": 1590,
      "user_id": 99,
      "id": 12
    },
    {
      "post_id": 1679,
      "user_id": 99,
      "id": 13
    },
    {
      "post_id": 1686,
      "user_id": 99,
      "id": 14
    }
  ]
}